ndrop/__init__.py
ndrop/__main__.py
ndrop/__main_tk__.py
ndrop/about.py
ndrop/dukto.py
ndrop/hdpitk.py
ndrop/hfs.py
ndrop/netdrop.py
ndrop/nitroshare.py
ndrop/transport.py
ndrop/image/AndroidLogo.png
ndrop/image/AppleLogo.png
ndrop/image/BackIcon.png
ndrop/image/BackIconDark.png
ndrop/image/BackTile.png
ndrop/image/BlackberryLogo.png
ndrop/image/BottomShadow.png
ndrop/image/ConfigIcon.png
ndrop/image/DuktoMetroIcon.png
ndrop/image/IosLogo.png
ndrop/image/IpLogo.png
ndrop/image/LinuxLogo.png
ndrop/image/MoreIcon.png
ndrop/image/OpenFolderIcon.png
ndrop/image/PanelGradient.png
ndrop/image/PcLogo.png
ndrop/image/RecentFile.png
ndrop/image/RecentFiles.png
ndrop/image/RecentText.png
ndrop/image/ShowIpIcon - Copia.png
ndrop/image/ShowIpIcon.png
ndrop/image/SmartphoneLogo.png
ndrop/image/SymbianLogo.png
ndrop/image/TileGradient.png
ndrop/image/TopShadow.png
ndrop/image/UnknownLogo.png
ndrop/image/WindowsLogo.png
ndrop/image/WindowsPhoneLogo.png
ndrop/image/dukto.png
ndrop/image/hfs.png
ndrop/image/ndrop.ico
ndrop/image/ndrop.png
ndrop/image/nitroshare.png
tkinterdnd2/TkinterDnD.py
tkinterdnd2/__init__.py
tkinterdnd2/tkdnd/linux64/libtkdnd2.9.2.so
tkinterdnd2/tkdnd/linux64/pkgIndex.tcl
tkinterdnd2/tkdnd/linux64/tkdnd.tcl
tkinterdnd2/tkdnd/linux64/tkdnd_compat.tcl
tkinterdnd2/tkdnd/linux64/tkdnd_generic.tcl
tkinterdnd2/tkdnd/linux64/tkdnd_macosx.tcl
tkinterdnd2/tkdnd/linux64/tkdnd_unix.tcl
tkinterdnd2/tkdnd/linux64/tkdnd_utils.tcl
tkinterdnd2/tkdnd/linux64/tkdnd_windows.tcl
tkinterdnd2/tkdnd/osx64/libtkdnd2.9.2.dylib
tkinterdnd2/tkdnd/osx64/pkgIndex.tcl
tkinterdnd2/tkdnd/osx64/tkdnd.tcl
tkinterdnd2/tkdnd/osx64/tkdnd_compat.tcl
tkinterdnd2/tkdnd/osx64/tkdnd_generic.tcl
tkinterdnd2/tkdnd/osx64/tkdnd_macosx.tcl
tkinterdnd2/tkdnd/osx64/tkdnd_unix.tcl
tkinterdnd2/tkdnd/osx64/tkdnd_utils.tcl
tkinterdnd2/tkdnd/osx64/tkdnd_windows.tcl
tkinterdnd2/tkdnd/win64/libtkdnd2.9.2.dll
tkinterdnd2/tkdnd/win64/pkgIndex.tcl
tkinterdnd2/tkdnd/win64/tkdnd.tcl
ndrop-1.5.10.dist-info/LICENSE
ndrop-1.5.10.dist-info/LICENSE.996ICU
ndrop-1.5.10.dist-info/METADATA
ndrop-1.5.10.dist-info/WHEEL
ndrop-1.5.10.dist-info/entry_points.txt
ndrop-1.5.10.dist-info/top_level.txt
ndrop-1.5.10.dist-info/RECORD
