Metadata-Version: 2.1
Name: ndrop
Version: 1.5.10
Summary: File Transfer Tool.
Home-page: https://github.com/liuyug/ndrop.git
Author-email: liuyug@gmail.com
License: MIT
Platform: noarch
Requires-Python: >=3.6
Requires-Dist: appdirs
Requires-Dist: ifaddr
Requires-Dist: pillow
Requires-Dist: tqdm
